bio2bel_sider/__init__.py
bio2bel_sider/__main__.py
bio2bel_sider/cli.py
bio2bel_sider/constants.py
bio2bel_sider/manager.py
bio2bel_sider/models.py
bio2bel_sider/parser.py
bio2bel_sider/web.py
bio2bel_sider-0.0.1.dist-info/LICENSE
bio2bel_sider-0.0.1.dist-info/METADATA
bio2bel_sider-0.0.1.dist-info/WHEEL
bio2bel_sider-0.0.1.dist-info/entry_points.txt
bio2bel_sider-0.0.1.dist-info/top_level.txt
bio2bel_sider-0.0.1.dist-info/RECORD
