Metadata-Version: 2.1
Name: bio2bel-sider
Version: 0.0.1
Summary: Bio2BEL SIDER.
Home-page: https://github.com/bio2bel/sider
Author: Charles Tapley Hoyt
Author-email: charles.hoyt@scai.fraunhofer.de
Maintainer: Charles Tapley Hoyt
Maintainer-email: charles.hoyt@scai.fraunhofer.de
License: MIT
Keywords: Biological Expression Language,Drug Indications,Drug Side Effects
Platform: UNKNOWN
Classifier: Development Status :: 1 - Planning
Classifier: Intended Audience :: Developers
Classifier: Programming Language :: Python
Classifier: Programming Language :: Python :: 3.7
Classifier: Programming Language :: Python :: 3.6
Classifier: Programming Language :: Python :: 3 :: Only
Classifier: License :: OSI Approved :: MIT License
Requires-Python: >=3.6
Requires-Dist: pybel (<0.13.0,>=0.12.0)
Requires-Dist: bio2bel (<0.3.0,>=0.2.0)
Requires-Dist: click
Requires-Dist: pandas
Requires-Dist: sqlalchemy
Requires-Dist: tqdm
Provides-Extra: docs
Requires-Dist: sphinx ; extra == 'docs'
Requires-Dist: sphinx-rtd-theme ; extra == 'docs'
Requires-Dist: sphinx-click ; extra == 'docs'
Requires-Dist: sphinx-autodoc-typehints ; extra == 'docs'
